setup.py
abi/__init__.py
abi/base.py
abi.egg-info/PKG-INFO
abi.egg-info/SOURCES.txt
abi.egg-info/dependency_links.txt
abi.egg-info/requires.txt
abi.egg-info/top_level.txt