Metadata-Version: 1.0
Name: abi
Version: 0.1.0
Summary: DLL ABI loader
Home-page: http://github.com/oakfang/abi
Author: Alon Niv
Author-email: oakfang@gmail.com
License: MIT
Platform: UNKNOWN
